getstanza/README.md
getstanza/__init__.py
getstanza/client.py
getstanza/configuration.py
getstanza/errors/__init__.py
getstanza/errors/hub/__init__.py
getstanza/errors/hub/hub_error.py
getstanza/errors/sdk/__init__.py
getstanza/errors/sdk/guard_error.py
getstanza/guard.py
getstanza/hub/__init__.py
getstanza/hub/configuration_manager.py
getstanza/hub/poller.py
getstanza/hub/telemetry.py
getstanza/otel/__init__.py
getstanza/otel/meter.py
getstanza/otel/tracer.py
getstanza/propagation.py
getstanza/tests/__init__.py
getstanza/tests/conftest.py
getstanza/tests/fixtures/__init__.py
getstanza/tests/fixtures/configurations.py
getstanza/tests/fixtures/grpc.py
getstanza/tests/fixtures/guards.py
getstanza/tests/test_guard.py
getstanza/tests/utils/__init__.py
getstanza_fastapi/README.md
getstanza_fastapi/__init__.py
getstanza_fastapi/fastapi_client.py
getstanza_fastapi/fastapi_guard.py
getstanza_fastapi/tests/test_fastapi_client.py
getstanza_fastapi/tests/test_fastapi_guard.py
getstanza_requests/README.md
getstanza_requests/__init__.py
getstanza_requests/stanza_session.py
getstanza_sqs/README.md
getstanza_sqs/__init__.py
getstanza_sqs/exceptions.py
getstanza_sqs/sqs_client.py
getstanza_sqs/sqs_guard.py
stanza/hub/v1/README.md
stanza/hub/v1/auth_pb2.py
stanza/hub/v1/auth_pb2.pyi
stanza/hub/v1/auth_pb2_grpc.py
stanza/hub/v1/common_pb2.py
stanza/hub/v1/common_pb2.pyi
stanza/hub/v1/common_pb2_grpc.py
stanza/hub/v1/config_pb2.py
stanza/hub/v1/config_pb2.pyi
stanza/hub/v1/config_pb2_grpc.py
stanza/hub/v1/health_pb2.py
stanza/hub/v1/health_pb2.pyi
stanza/hub/v1/health_pb2_grpc.py
stanza/hub/v1/quota_pb2.py
stanza/hub/v1/quota_pb2.pyi
stanza/hub/v1/quota_pb2_grpc.py
stanza/hub/v1/stream_pb2.py
stanza/hub/v1/stream_pb2.pyi
stanza/hub/v1/stream_pb2_grpc.py
stanza/hub/v1/usage_pb2.py
stanza/hub/v1/usage_pb2.pyi
stanza/hub/v1/usage_pb2_grpc.py
getstanza-0.0.3b1.dist-info/METADATA
getstanza-0.0.3b1.dist-info/WHEEL
getstanza-0.0.3b1.dist-info/RECORD
