Metadata-Version: 2.1
Name: getstanza
Version: 0.0.3b1
Summary: Python SDK for adding Stanza Systems fault tolerance to your python 3 service.
Home-page: http://www.stanza.systems
Keywords: fault-tolerance,traffic,traffic-control,stanza
Author: Stanza Systems
Author-email: hello@sre.is
Requires-Python: >=3.9,<4.0
Classifier: Development Status :: 4 - Beta
Classifier: Intended Audience :: Developers
Classifier: License :: OSI Approved :: Apache Software License
Classifier: Programming Language :: Python :: 3
Classifier: Programming Language :: Python :: 3.9
Classifier: Programming Language :: Python :: 3.10
Classifier: Programming Language :: Python :: 3.11
Classifier: Programming Language :: Python :: 3.12
Classifier: Topic :: Software Development :: Libraries
Requires-Dist: boto3 (>=1.34.32,<2.0.0)
Requires-Dist: fastapi (>=0.109.0,<0.110.0)
Requires-Dist: grpcio (>=1.60.0,<2.0.0)
Requires-Dist: opentelemetry-api (>=1.20.0,<2.0.0)
Requires-Dist: opentelemetry-exporter-otlp-proto-grpc (>=1.20.0,<2.0.0)
Requires-Dist: opentelemetry-sdk (>=1.20.0,<2.0.0)
Requires-Dist: protoc-gen-openapiv2 (>=0.0.1,<0.0.2)
Requires-Dist: python-dateutil (>=2.8.2,<3.0.0)
Requires-Dist: requests (>=2.31.0,<3.0.0)
Project-URL: Repository, https://github.com/StanzaSystems/sdk-python
